unigui-2.4.4.dist-info/METADATA
unigui-2.4.4.dist-info/WHEEL
unigui-2.4.4.dist-info/licenses/LICENSE
unigui/__init__.py
unigui/autotest.py
unigui/common.py
unigui/containers.py
unigui/guielements.py
unigui/proxy.py
unigui/reloader.py
unigui/server.py
unigui/tables.py
unigui/users.py
unigui/utils.py
unigui/web/css/169.3abcdd94.css
unigui/web/css/app.31d6cfe0.css
unigui/web/css/vendor.9ed7638d.css
unigui/web/favicon.ico
unigui/web/fonts/KFOkCnqEu92Fr1MmgVxIIzQ.68bb21d0.woff
unigui/web/fonts/KFOlCnqEu92Fr1MmEU9fBBc-.48af7707.woff
unigui/web/fonts/KFOlCnqEu92Fr1MmSU5fBBc-.c2f7ab22.woff
unigui/web/fonts/KFOlCnqEu92Fr1MmWUlfBBc-.77ecb942.woff
unigui/web/fonts/KFOlCnqEu92Fr1MmYUtfBBc-.f5677eb2.woff
unigui/web/fonts/KFOmCnqEu92Fr1Mu4mxM.f1e2a767.woff
unigui/web/fonts/flUhRq6tzZclQEJ-Vdg-IuiaDsNa.4d73cb90.woff
unigui/web/fonts/flUhRq6tzZclQEJ-Vdg-IuiaDsNcIhQ8tQ.c5371cfb.woff2
unigui/web/icons/favicon-128x128.png
unigui/web/icons/favicon-16x16.png
unigui/web/icons/favicon-32x32.png
unigui/web/icons/favicon-96x96.png
unigui/web/index.html
unigui/web/js/169.f952e294.js
unigui/web/js/193.283445be.js
unigui/web/js/430.591e9a73.js
unigui/web/js/app.ba94719f.js
unigui/web/js/vendor.d6797c01.js
unisi/__init__.py
unigui-2.4.4.dist-info/RECORD
