Metadata-Version: 2.1
Name: unigui
Version: 2.4.4
Summary: Unigui - Universal GUI Framework and protocol
Author-Email: Georgii Dernovyi <g.dernovoy@gmail.com>
License: MIT
Project-URL: Homepage, https://github.com/Claus1/unigui
Requires-Python: >=3.8
Requires-Dist: aiohttp
Requires-Dist: jsoncomparison
Requires-Dist: jsonpickle
Requires-Dist: pandas
Requires-Dist: requests
Requires-Dist: watchdog
Requires-Dist: websockets
